derivative_mode/__init__.py
derivative_mode/derivative.py
derivative_mode-0.5.dist-info/METADATA
derivative_mode-0.5.dist-info/WHEEL
derivative_mode-0.5.dist-info/top_level.txt
derivative_mode-0.5.dist-info/RECORD
