Metadata-Version: 2.1
Name: derivative-mode
Version: 0.5
Summary: This module destined to calculation of derivatives using numerical methods
Home-page: https://github.com/Mun-Robbery
Author: antrisole
Author-email: gleb.zar.03@mail.ru
Project-URL: GitHub, https://github.com/Mun-Robbery
Keywords: numerical derivative
Classifier: Programming Language :: Python :: 3.11
Classifier: License :: OSI Approved :: MIT License
Classifier: Operating System :: OS Independent
Requires-Python: >=3.6
Requires-Dist: requests >=2.25.1
